netmiko_2fa_google_authenticator/__init__.py
netmiko_2fa_google_authenticator/ssh_google_authenticator_2fa.py
netmiko_2fa_google_authenticator-0.2.dist-info/LICENSE
netmiko_2fa_google_authenticator-0.2.dist-info/METADATA
netmiko_2fa_google_authenticator-0.2.dist-info/NOTICE
netmiko_2fa_google_authenticator-0.2.dist-info/WHEEL
netmiko_2fa_google_authenticator-0.2.dist-info/top_level.txt
netmiko_2fa_google_authenticator-0.2.dist-info/RECORD
