Metadata-Version: 2.1
Name: netmiko-2fa-google-authenticator
Version: 0.2
Summary: Out of tree netmiko driver for 2FA with google-authenticator
Home-page: https://github.com/cancom-austria-network-solutions/netmiko_2fa_google_authenticator
Author: Wilhelm Putz
Author-email: wilhelm.putz@cancom.com
License: ASL V2
Platform: UNKNOWN
Classifier: License :: OSI Approved :: Apache Software License
Classifier: Programming Language :: Python :: 3.7
Classifier: Programming Language :: Python :: 3.8
Classifier: Topic :: System :: Installation/Setup
Classifier: Topic :: System :: Systems Administration
Classifier: Topic :: Utilities
Requires-Python: >=3.7
License-File: LICENSE
License-File: NOTICE
Requires-Dist: netmiko (>=4.3)
